envsecure/__init__.py
envsecure/cli.py
envsecure/core.py
envsecure-1.0.0.dist-info/licenses/LICENSE
envsecure-1.0.0.dist-info/METADATA
envsecure-1.0.0.dist-info/WHEEL
envsecure-1.0.0.dist-info/entry_points.txt
envsecure-1.0.0.dist-info/top_level.txt
envsecure-1.0.0.dist-info/RECORD
