Metadata-Version: 2.4
Name: envsecure
Version: 1.0.0
Summary: A CLI tool to securely encrypt and decrypt .env files using AES-256
Author: Your Name
Author-email: Karan Taware <karan.taware531@gmail.com>
License: MIT
Project-URL: Homepage, https://github.com/karantaware531/envsecure/README.md
Project-URL: Repository, https://github.com/karantaware531/envsecure
Keywords: env,encryption,aes,cli,dotenv,security
Classifier: Programming Language :: Python :: 3
Classifier: License :: OSI Approved :: MIT License
Classifier: Operating System :: OS Independent
Classifier: Environment :: Console
Requires-Python: >=3.7
License-File: LICENSE
Dynamic: author
Dynamic: license-file
